{"title":"CHICANO RAP CAPONE-E A Dedicated 2 the Oldies","uid":9845663,"size":59610224,"categoryP":"audio","categoryS":"other","magnet":"?xt=urn:btih:0382de4dc76f1dfc94dab3d1c81da77b74cc6ad5&amp;dn=CHICANO+RAP+CAPONE-E+A+Dedicated+2+the+Oldies&amp;tr=udp%3A%2F%2Ftracker.openbittorrent.com%3A80&amp;tr=udp%3A%2F%2Fopen.demonii.com%3A1337&amp;tr=udp%3A%2F%2Ftracker.coppersurfer.tk%3A6969&amp;tr=udp%3A%2F%2Fexodus.desync.com%3A6969","seeders":1,"leechers":0,"uploader":"Chessplay1714","files":14,"time":1396063804,"description":"                          CAPONE-E A Dedicated 2 the Oldies\n\n\n\n\t\nIntroduction\n\t\nLook Over Your Shoulder\n\t\nTake a Chance\n\t\nAngel Baby 2003\n\t\nWhat Are You Bumpin\n\t\nCan't Be Stopped\n\t\nHi Power Gangster\n\t\nWanna Be Freaked\n\t\nThe Life We Live\n\t\nSouthside Radio\n\t\nGangster Lovin'\n\t\nI Ain't the One\n\t\nNever Be the Same Again\n\t\nYou're the One for Me\n\n","torrent":{"xt":"urn:btih:0382de4dc76f1dfc94dab3d1c81da77b74cc6ad5","amp;dn":"CHICANO+RAP+CAPONE-E+A+Dedicated+2+the+Oldies","amp;tr":["udp%3A%2F%2Ftracker.openbittorrent.com%3A80","udp%3A%2F%2Fopen.demonii.com%3A1337","udp%3A%2F%2Ftracker.coppersurfer.tk%3A6969","udp%3A%2F%2Fexodus.desync.com%3A6969"],"infoHash":"0382de4dc76f1dfc94dab3d1c81da77b74cc6ad5","infoHashBuffer":{"type":"Buffer","data":[3,130,222,77,199,111,29,252,148,218,179,209,200,29,167,123,116,204,106,213]},"announce":[],"urlList":[]}}