{"title":"Penthouse All Natural Brunettes Get Dirty XXX 720p WEBRiP WMV-GU","uid":13732764,"size":5655327084,"categoryP":"porn","categoryS":"movies","magnet":"?xt=urn:btih:05726c5b7157fdf2b1ab7ee541d4c8d606d51863&amp;dn=Penthouse+All+Natural+Brunettes+Get+Dirty+XXX+720p+WEBRiP+WMV-GU&amp;tr=udp%3A%2F%2Ftracker.leechers-paradise.org%3A6969&amp;tr=udp%3A%2F%2Fzer0day.ch%3A1337&amp;tr=udp%3A%2F%2Fopen.demonii.com%3A1337&amp;tr=udp%3A%2F%2Ftracker.coppersurfer.tk%3A6969&amp;tr=udp%3A%2F%2Fexodus.desync.com%3A6969","seeders":1,"leechers":0,"uploader":"0-DayXXX","files":1,"time":1457026604,"description":"------------------------------------------------\nPenthouse.All.Natural.Brunettes.Get.Dirty.XXX.720p.WEBRiP.WMV-GUSH\n------------------------------------------------\nScreenshot(s): \nhttp://imgsay.com/?v=370449 \n\n------------------------------------------------\nInfo(s):\nFormat:\t\tWindows Media\nSize:\t\t5.27 GiB\nDuration:\t1h 33min\nResolution:\t1280x720\nBitrate:\t7741Kbps\n------------------------------------------------\n         ** More 0-DayXXX Uploads ** \nhttp://youpornbook.com\n------------------------------------------------\nIf you like this torrent, please post a comment!\n            Don't forget to seed!","torrent":{"xt":"urn:btih:05726c5b7157fdf2b1ab7ee541d4c8d606d51863","amp;dn":"Penthouse+All+Natural+Brunettes+Get+Dirty+XXX+720p+WEBRiP+WMV-GU","amp;tr":["udp%3A%2F%2Ftracker.leechers-paradise.org%3A6969","udp%3A%2F%2Fzer0day.ch%3A1337","udp%3A%2F%2Fopen.demonii.com%3A1337","udp%3A%2F%2Ftracker.coppersurfer.tk%3A6969","udp%3A%2F%2Fexodus.desync.com%3A6969"],"infoHash":"05726c5b7157fdf2b1ab7ee541d4c8d606d51863","infoHashBuffer":{"type":"Buffer","data":[5,114,108,91,113,87,253,242,177,171,126,229,65,212,200,214,6,213,24,99]},"announce":[],"urlList":[]}}