{"title":"Diario Deportivo Marca 10.04.14","uid":9931672,"size":14845981,"categoryP":"other","categoryS":"other","magnet":"?xt=urn:btih:1df85b4ed64569824d814a0913c4972272bcee6d&amp;dn=Diario+Deportivo+Marca+10.04.14&amp;tr=udp%3A%2F%2Ftracker.openbittorrent.com%3A80&amp;tr=udp%3A%2F%2Fopen.demonii.com%3A1337&amp;tr=udp%3A%2F%2Ftracker.coppersurfer.tk%3A6969&amp;tr=udp%3A%2F%2Fexodus.desync.com%3A6969","seeders":1,"leechers":0,"uploader":"virana","files":1,"time":1397110604,"description":"Marca 10.04.14","torrent":{"xt":"urn:btih:1df85b4ed64569824d814a0913c4972272bcee6d","amp;dn":"Diario+Deportivo+Marca+10.04.14","amp;tr":["udp%3A%2F%2Ftracker.openbittorrent.com%3A80","udp%3A%2F%2Fopen.demonii.com%3A1337","udp%3A%2F%2Ftracker.coppersurfer.tk%3A6969","udp%3A%2F%2Fexodus.desync.com%3A6969"],"infoHash":"1df85b4ed64569824d814a0913c4972272bcee6d","infoHashBuffer":{"type":"Buffer","data":[29,248,91,78,214,69,105,130,77,129,74,9,19,196,151,34,114,188,238,109]},"announce":[],"urlList":[]}}