{"title":"Al Di Meola - Tour De Force -  Live (1982) [EAC-APE]","uid":7898269,"size":276186867,"categoryP":"audio","categoryS":"flac","magnet":"?xt=urn:btih:1ebcda147c5302042ab51c634feb1dbb9f505b14&amp;dn=Al+Di+Meola+-+Tour+De+Force+-++Live+%281982%29+%5BEAC-APE%5D&amp;tr=udp%3A%2F%2Ftracker.openbittorrent.com%3A80&amp;tr=udp%3A%2F%2Fopen.demonii.com%3A1337&amp;tr=udp%3A%2F%2Ftracker.coppersurfer.tk%3A6969&amp;tr=udp%3A%2F%2Fexodus.desync.com%3A6969","seeders":1,"leechers":1,"uploader":"qculfj","files":12,"time":1354898305,"description":"1. Elegant Gypsy Suite\n2. Nena\n3. Advantage\n4. Egyptian Danza\n5. Race With Devil on Spanish Highway\n6. Cruisin'","torrent":{"xt":"urn:btih:1ebcda147c5302042ab51c634feb1dbb9f505b14","amp;dn":"Al+Di+Meola+-+Tour+De+Force+-++Live+%281982%29+%5BEAC-APE%5D","amp;tr":["udp%3A%2F%2Ftracker.openbittorrent.com%3A80","udp%3A%2F%2Fopen.demonii.com%3A1337","udp%3A%2F%2Ftracker.coppersurfer.tk%3A6969","udp%3A%2F%2Fexodus.desync.com%3A6969"],"infoHash":"1ebcda147c5302042ab51c634feb1dbb9f505b14","infoHashBuffer":{"type":"Buffer","data":[30,188,218,20,124,83,2,4,42,181,28,99,79,235,29,187,159,80,91,20]},"announce":[],"urlList":[]}}