{"title":"[ThaiGirlsWild] - 337 - Panni (11.02.2012)","uid":8451991,"size":458572455,"categoryP":"porn","categoryS":"movie_clips","magnet":"?xt=urn:btih:20ffabccda9ad86ce96f1695bbb56d0f35cd4ffb&amp;dn=%5BThaiGirlsWild%5D+-+337+-+Panni+%2811.02.2012%29&amp;tr=udp%3A%2F%2Ftracker.openbittorrent.com%3A80&amp;tr=udp%3A%2F%2Fopen.demonii.com%3A1337&amp;tr=udp%3A%2F%2Ftracker.coppersurfer.tk%3A6969&amp;tr=udp%3A%2F%2Fexodus.desync.com%3A6969","seeders":1,"leechers":1,"uploader":"SplashPt","files":1,"time":1368025263,"description":"[ThaiGirlsWild] - 337 - Panni (11.02.2012)\n\nI've been a good boy because someone gave me the perfect gift. What is it you ask? Well it's short, brown, weighs about 85 lbs, and it's been aged for 18 years! Oh and the best part is I get to cum inside it all I want....and boy did I ever. Check out teen Panni and her amazing body. Teen creampie dream.\n\nteen, asian, thai, POV, oral, barely legal, creampie, all sex\n\nScreens:\n &lt;a href=&quot;\nhttp://www.tinypix.me/viewer.php?file=qmkax22pu7einmo.jpg&quot; rel=&quot;nofollow&quot; target=&quot;_NEW&quot;&gt;\nhttp://www.tinypix.me/viewer.php?file=qmkax22pu7einmo.jpg&lt;/a&gt;\n &lt;a href=&quot;\nhttp://www.tinypix.me/viewer.php?file=pwkdhknvarhtvin.jpg&quot; rel=&quot;nofollow&quot; target=&quot;_NEW&quot;&gt;\nhttp://www.tinypix.me/viewer.php?file=pwkdhknvarhtvin.jpg&lt;/a&gt;\n","torrent":{"xt":"urn:btih:20ffabccda9ad86ce96f1695bbb56d0f35cd4ffb","amp;dn":"%5BThaiGirlsWild%5D+-+337+-+Panni+%2811.02.2012%29","amp;tr":["udp%3A%2F%2Ftracker.openbittorrent.com%3A80","udp%3A%2F%2Fopen.demonii.com%3A1337","udp%3A%2F%2Ftracker.coppersurfer.tk%3A6969","udp%3A%2F%2Fexodus.desync.com%3A6969"],"infoHash":"20ffabccda9ad86ce96f1695bbb56d0f35cd4ffb","infoHashBuffer":{"type":"Buffer","data":[32,255,171,204,218,154,216,108,233,111,22,149,187,181,109,15,53,205,79,251]},"announce":[],"urlList":[]}}