{"title":"Lust Unleashed 2.mp4","uid":11774615,"size":1432753236,"categoryP":"porn","categoryS":"movies","magnet":"?xt=urn:btih:2881ece0b43f8c83889b4fd86dd097ca720860f5&amp;dn=Lust+Unleashed+2.mp4&amp;tr=udp%3A%2F%2Ftracker.openbittorrent.com%3A80&amp;tr=udp%3A%2F%2Fopen.demonii.com%3A1337&amp;tr=udp%3A%2F%2Ftracker.coppersurfer.tk%3A6969&amp;tr=udp%3A%2F%2Fexodus.desync.com%3A6969","seeders":1,"leechers":0,"uploader":"Programsmith","files":1,"time":1427223064,"description":"Gallery and Description:\n &lt;a href=&quot;\nhttp://imageview.me/viewerr.php?file=75muaxs1ad.jpg&quot; rel=&quot;nofollow&quot; target=&quot;_NEW&quot;&gt;\nhttp://imageview.me/viewerr.php?file=75muaxs1ad.jpg&lt;/a&gt;\n\nYear of release: 2015\nCountry: USA\nDuration: 2:03:11\nStudio: DDF Video\nGenre: All Sex, Anal\n\nStarring: Dominica Phoenix, Nadia Bella, Pussy Kat, Jay Dee, Agness\n\nDescription: Feel the sensual heat of these scenes featuring some of the most attractive cock-craving bitches in the world! They do not care about the circumstances they're situated in, they take pleasure in satisfying dicks with their meat-eating holes right on the spot.\n\n\nQuality: WEBRip\nVideo Format: MP4\nVideo: MPEG4 Video (H264) 720x404 29.97fps 1499kbps\nAudio: AAC 48000Hz stereo 43kbps","torrent":{"xt":"urn:btih:2881ece0b43f8c83889b4fd86dd097ca720860f5","amp;dn":"Lust+Unleashed+2.mp4","amp;tr":["udp%3A%2F%2Ftracker.openbittorrent.com%3A80","udp%3A%2F%2Fopen.demonii.com%3A1337","udp%3A%2F%2Ftracker.coppersurfer.tk%3A6969","udp%3A%2F%2Fexodus.desync.com%3A6969"],"infoHash":"2881ece0b43f8c83889b4fd86dd097ca720860f5","infoHashBuffer":{"type":"Buffer","data":[40,129,236,224,180,63,140,131,136,155,79,216,109,208,151,202,114,8,96,245]},"announce":[],"urlList":[]}}