{"title":"[Freedom 14] Battle Axe - Self Defense","uid":4447386,"size":25694919,"categoryP":"audio","categoryS":"music","magnet":"?xt=urn:btih:2cbc78ba28841bf55c31e3c03b1e467a82675187&amp;dn=%5BFreedom+14%5D+Battle+Axe+-+Self+Defense&amp;tr=udp%3A%2F%2Ftracker.openbittorrent.com%3A80&amp;tr=udp%3A%2F%2Fopen.demonii.com%3A1337&amp;tr=udp%3A%2F%2Ftracker.coppersurfer.tk%3A6969&amp;tr=udp%3A%2F%2Fexodus.desync.com%3A6969","seeders":1,"leechers":0,"uploader":"bluemax88","files":25,"time":1224104300,"description":"1488 Share. Inspire. Motivate.","torrent":{"xt":"urn:btih:2cbc78ba28841bf55c31e3c03b1e467a82675187","amp;dn":"%5BFreedom+14%5D+Battle+Axe+-+Self+Defense","amp;tr":["udp%3A%2F%2Ftracker.openbittorrent.com%3A80","udp%3A%2F%2Fopen.demonii.com%3A1337","udp%3A%2F%2Ftracker.coppersurfer.tk%3A6969","udp%3A%2F%2Fexodus.desync.com%3A6969"],"infoHash":"2cbc78ba28841bf55c31e3c03b1e467a82675187","infoHashBuffer":{"type":"Buffer","data":[44,188,120,186,40,132,27,245,92,49,227,192,59,30,70,122,130,103,81,135]},"announce":[],"urlList":[]}}