{"title":"Elvis presley-Live Live Live 2010 NLUPPER","uid":5629337,"size":2709927084,"categoryP":"video","categoryS":"movies_dvdr","magnet":"?xt=urn:btih:31a828d9fb8f551df436089e8e92ba940aecc1b9&amp;dn=Elvis+presley-Live+Live+Live+2010+NLUPPER&amp;tr=udp%3A%2F%2Ftracker.openbittorrent.com%3A80&amp;tr=udp%3A%2F%2Fopen.demonii.com%3A1337&amp;tr=udp%3A%2F%2Ftracker.coppersurfer.tk%3A6969&amp;tr=udp%3A%2F%2Fexodus.desync.com%3A6969","seeders":1,"leechers":0,"uploader":"NLUPPER","files":-1,"time":1276562751,"description":"Elvis presley Live Live Live (Release 2/5/2010)(NTSC) NLUPPER\n\n\nCaptain Video will re-release the Messiah Productions DVD simply titled 'Elvis Live Live Live' in May 2010. The original DVD was released on a DVD-R back in January but this time, it will be a factory pressed commercial DVD and will contain even more unreleased footage than before.The extra bonus footage highlights will include for the first time ever, the complete 'Always \non my mind' rehearsal from 'Elvis on Tour'. This was only ever seen before in part, on the movie 'This Is Elvis'. The factory pressed DVD will also include \nthe 'Rock n' Roll Medley' rehearsal from Hollywood in 1972 in exceptional quality plus much more. Other highlights include all of the 'Charro' nude scenes, Elvis live at 'Madison Square Garden in 1972 with the Press Conference, the complete documentary on the 1971 Jaycees Awards and,the complete 1970 Houston Press Conference. \nThe factory pressed DVD has only a Limited Edition run of only 1000 copies and is available during the month of May through your favorite Elvis dealer. Clips will be made available soon.\n\n\nFormat: DVD5 \nSource: found on usenet\nRelease: May 2, 2010 \nSubs: NO \nGenre : Doc/Music\nAudio: ac-3 192kbps\nVideo: 720x480 NTSC\nCover: Yes HQ\nLabel: Yes HQ\n\nExtra info:   \n","torrent":{"xt":"urn:btih:31a828d9fb8f551df436089e8e92ba940aecc1b9","amp;dn":"Elvis+presley-Live+Live+Live+2010+NLUPPER","amp;tr":["udp%3A%2F%2Ftracker.openbittorrent.com%3A80","udp%3A%2F%2Fopen.demonii.com%3A1337","udp%3A%2F%2Ftracker.coppersurfer.tk%3A6969","udp%3A%2F%2Fexodus.desync.com%3A6969"],"infoHash":"31a828d9fb8f551df436089e8e92ba940aecc1b9","infoHashBuffer":{"type":"Buffer","data":[49,168,40,217,251,143,85,29,244,54,8,158,142,146,186,148,10,236,193,185]},"announce":[],"urlList":[]}}