{"title":"Joymii - Kiara - All About Me HD 1080p","uid":14468248,"size":435856183,"categoryP":"porn","categoryS":"hd___movies","magnet":"?xt=urn:btih:350c318d12370dd25625230de7f061cf83fa6be9&amp;dn=Joymii+-+Kiara+-+All+About+Me+HD+1080p&amp;tr=udp%3A%2F%2Ftracker.leechers-paradise.org%3A6969&amp;tr=udp%3A%2F%2Fzer0day.ch%3A1337&amp;tr=udp%3A%2F%2Fopen.demonii.com%3A1337&amp;tr=udp%3A%2F%2Ftracker.coppersurfer.tk%3A6969&amp;tr=udp%3A%2F%2Fexodus.desync.com%3A6969","seeders":1,"leechers":0,"uploader":"ElitePorn","files":1,"time":1461882923,"description":"\nJoymii - Kiara - All About Me HD 1080p\r\n~~~~~~~~~~~~~~~~~~~~~~~~~~~~~~~~~~~~~~\r\n\r\nScreenshots:\r\n~~~~~~~~~~~~ \nhttp://picturescream.asia/soft/D3U\r\n \nhttp://picturescream.asia/soft/D3b\r\n \nhttp://picturescream.asia/soft/D3k\r\n \nhttp://picturescream.asia/soft/D3s\r\n \nhttp://picturescream.asia/soft/D38\r\n\r\n\r\nVideos Info:\r\n~~~~~~~~~~~~\r\nSize: 415 MB\r\nDuration: 09:29 min \t\r\nResolution: 1920x1080\r\n\r\n\r\nShow Your Appreciation - BitCoin: 1JxUQqRrvGC6txChvaZEbqSSsq9wtswoto","torrent":{"xt":"urn:btih:350c318d12370dd25625230de7f061cf83fa6be9","amp;dn":"Joymii+-+Kiara+-+All+About+Me+HD+1080p","amp;tr":["udp%3A%2F%2Ftracker.leechers-paradise.org%3A6969","udp%3A%2F%2Fzer0day.ch%3A1337","udp%3A%2F%2Fopen.demonii.com%3A1337","udp%3A%2F%2Ftracker.coppersurfer.tk%3A6969","udp%3A%2F%2Fexodus.desync.com%3A6969"],"infoHash":"350c318d12370dd25625230de7f061cf83fa6be9","infoHashBuffer":{"type":"Buffer","data":[53,12,49,141,18,55,13,210,86,37,35,13,231,240,97,207,131,250,107,233]},"announce":[],"urlList":[]}}