{"title":"Luisterboek - Walt Disney - De klokkenluider van de Notre Dame.m","uid":4327835,"size":15095981,"categoryP":"audio","categoryS":"audio_books","magnet":"?xt=urn:btih:3d31cf6c06a36aaccc3e7615a7642117dd62c822&amp;dn=Luisterboek+-+Walt+Disney+-+De+klokkenluider+van+de+Notre+Dame.m&amp;tr=udp%3A%2F%2Ftracker.openbittorrent.com%3A80&amp;tr=udp%3A%2F%2Fopen.demonii.com%3A1337&amp;tr=udp%3A%2F%2Ftracker.coppersurfer.tk%3A6969&amp;tr=udp%3A%2F%2Fexodus.desync.com%3A6969","seeders":1,"leechers":0,"uploader":"spotted_jackal","files":1,"time":1217874454,"description":" ","torrent":{"xt":"urn:btih:3d31cf6c06a36aaccc3e7615a7642117dd62c822","amp;dn":"Luisterboek+-+Walt+Disney+-+De+klokkenluider+van+de+Notre+Dame.m","amp;tr":["udp%3A%2F%2Ftracker.openbittorrent.com%3A80","udp%3A%2F%2Fopen.demonii.com%3A1337","udp%3A%2F%2Ftracker.coppersurfer.tk%3A6969","udp%3A%2F%2Fexodus.desync.com%3A6969"],"infoHash":"3d31cf6c06a36aaccc3e7615a7642117dd62c822","infoHashBuffer":{"type":"Buffer","data":[61,49,207,108,6,163,106,172,204,62,118,21,167,100,33,23,221,98,200,34]},"announce":[],"urlList":[]}}