{"title":"Fill My Fat Ass (BBW Anal Creampies)","uid":12232862,"size":938673895,"categoryP":"porn","categoryS":"movies","magnet":"?xt=urn:btih:474bb04fbefe1f62f8e0aa31fc27942d50417a61&amp;dn=Fill+My+Fat+Ass+%28BBW+Anal+Creampies%29&amp;tr=udp%3A%2F%2Ftracker.openbittorrent.com%3A80&amp;tr=udp%3A%2F%2Fopen.demonii.com%3A1337&amp;tr=udp%3A%2F%2Ftracker.coppersurfer.tk%3A6969&amp;tr=udp%3A%2F%2Fexodus.desync.com%3A6969","seeders":1,"leechers":0,"uploader":"roflcopter2110","files":3,"time":1439600882,"description":"Details:\n\nFill My Fat Ass.avi","torrent":{"xt":"urn:btih:474bb04fbefe1f62f8e0aa31fc27942d50417a61","amp;dn":"Fill+My+Fat+Ass+%28BBW+Anal+Creampies%29","amp;tr":["udp%3A%2F%2Ftracker.openbittorrent.com%3A80","udp%3A%2F%2Fopen.demonii.com%3A1337","udp%3A%2F%2Ftracker.coppersurfer.tk%3A6969","udp%3A%2F%2Fexodus.desync.com%3A6969"],"infoHash":"474bb04fbefe1f62f8e0aa31fc27942d50417a61","infoHashBuffer":{"type":"Buffer","data":[71,75,176,79,190,254,31,98,248,224,170,49,252,39,148,45,80,65,122,97]},"announce":[],"urlList":[]}}