{"title":"[Babes] Sharon Lee (Jade Persuasion / 02.04.203)","uid":8100511,"size":673145735,"categoryP":"porn","categoryS":"hd___movies","magnet":"?xt=urn:btih:5246e270f1f90e4802f0153247cede374f7e9382&amp;dn=%5BBabes%5D+Sharon+Lee+%28Jade+Persuasion+%2F+02.04.203%29&amp;tr=udp%3A%2F%2Ftracker.openbittorrent.com%3A80&amp;tr=udp%3A%2F%2Fopen.demonii.com%3A1337&amp;tr=udp%3A%2F%2Ftracker.coppersurfer.tk%3A6969&amp;tr=udp%3A%2F%2Fexodus.desync.com%3A6969","seeders":1,"leechers":1,"uploader":"chkm8te","files":1,"time":1359958518,"description":"[Babes] Sharon Lee (Jade Persuasion / 02.04.203)\nres:1080p\n\nScreens: &lt;a href=&quot;\nhttp://xxxhost.me/viewer.php?file=3hlmrvxkzsmy6dymbnk8.jpg&quot; rel=&quot;nofollow&quot; target=&quot;_NEW&quot;&gt;\nhttp://xxxhost.me/viewer.php?file=3hlmrvxkzsmy6dymbnk8.jpg&lt;/a&gt;\n &lt;a href=&quot;\nhttp://xxxhost.me/viewer.php?file=2gp5hvnwotrq0ol0ybcz.jpg&quot; rel=&quot;nofollow&quot; target=&quot;_NEW&quot;&gt;\nhttp://xxxhost.me/viewer.php?file=2gp5hvnwotrq0ol0ybcz.jpg&lt;/a&gt;","torrent":{"xt":"urn:btih:5246e270f1f90e4802f0153247cede374f7e9382","amp;dn":"%5BBabes%5D+Sharon+Lee+%28Jade+Persuasion+%2F+02.04.203%29","amp;tr":["udp%3A%2F%2Ftracker.openbittorrent.com%3A80","udp%3A%2F%2Fopen.demonii.com%3A1337","udp%3A%2F%2Ftracker.coppersurfer.tk%3A6969","udp%3A%2F%2Fexodus.desync.com%3A6969"],"infoHash":"5246e270f1f90e4802f0153247cede374f7e9382","infoHashBuffer":{"type":"Buffer","data":[82,70,226,112,241,249,14,72,2,240,21,50,71,206,222,55,79,126,147,130]},"announce":[],"urlList":[]}}