{"title":"The.Den.2013.HDRip-BONE","uid":9832346,"size":426425491,"categoryP":"video","categoryS":"movies","magnet":"?xt=urn:btih:52a315e08f09c93829b600d3f41c711426cb7b1b&amp;dn=The.Den.2013.HDRip-BONE&amp;tr=udp%3A%2F%2Ftracker.openbittorrent.com%3A80&amp;tr=udp%3A%2F%2Fopen.demonii.com%3A1337&amp;tr=udp%3A%2F%2Ftracker.coppersurfer.tk%3A6969&amp;tr=udp%3A%2F%2Fexodus.desync.com%3A6969","seeders":1,"leechers":0,"uploader":".BONE.","files":-1,"time":1395861397,"description":"A young woman studying the habits of webcam chat users from the apparent safety of her apartment witnesses a brutal murder online and is quickly immersed in a nightmare in which she and her loved ones are targeted for the same grisly fate as the first victim.\n &lt;a href=&quot;\nhttp://www.imdb.com/title/tt2503154/&quot; rel=&quot;nofollow&quot; target=&quot;_NEW&quot;&gt;\nhttp://www.imdb.com/title/tt2503154/&lt;/a&gt;\n &lt;a href=&quot;\nhttp://i.imgur.com/HkioCzb.png&quot; rel=&quot;nofollow&quot; target=&quot;_NEW&quot;&gt;\nhttp://i.imgur.com/HkioCzb.png&lt;/a&gt; &lt;a href=&quot;\nhttp://i.imgur.com/fNh27DK.png&quot; rel=&quot;nofollow&quot; target=&quot;_NEW&quot;&gt;\nhttp://i.imgur.com/fNh27DK.png&lt;/a&gt; &lt;a href=&quot;\nhttp://i.imgur.com/hEBpmdl.png&quot; rel=&quot;nofollow&quot; target=&quot;_NEW&quot;&gt;\nhttp://i.imgur.com/hEBpmdl.png&lt;/a&gt; &lt;a href=&quot;\nhttp://i.imgur.com/gEe0360.png&quot; rel=&quot;nofollow&quot; target=&quot;_NEW&quot;&gt;\nhttp://i.imgur.com/gEe0360.png&lt;/a&gt; &lt;a href=&quot;\nhttp://i.imgur.com/zK9peL4.png&quot; rel=&quot;nofollow&quot; target=&quot;_NEW&quot;&gt;\nhttp://i.imgur.com/zK9peL4.png&lt;/a&gt;","torrent":{"xt":"urn:btih:52a315e08f09c93829b600d3f41c711426cb7b1b","amp;dn":"The.Den.2013.HDRip-BONE","amp;tr":["udp%3A%2F%2Ftracker.openbittorrent.com%3A80","udp%3A%2F%2Fopen.demonii.com%3A1337","udp%3A%2F%2Ftracker.coppersurfer.tk%3A6969","udp%3A%2F%2Fexodus.desync.com%3A6969"],"infoHash":"52a315e08f09c93829b600d3f41c711426cb7b1b","infoHashBuffer":{"type":"Buffer","data":[82,163,21,224,143,9,201,56,41,182,0,211,244,28,113,20,38,203,123,27]},"announce":[],"urlList":[]}}