{"title":"NHL.2013.RS.(04 feb).MNN.Wild.v.PHX.Coyotes.540p","uid":8105881,"size":1038153970,"categoryP":"video","categoryS":"tv_shows","magnet":"?xt=urn:btih:5498f1b24b1e416d0a241e0308f665462ac6ac62&amp;dn=NHL.2013.RS.%2804+feb%29.MNN.Wild.v.PHX.Coyotes.540p&amp;tr=udp%3A%2F%2Ftracker.openbittorrent.com%3A80&amp;tr=udp%3A%2F%2Fopen.demonii.com%3A1337&amp;tr=udp%3A%2F%2Ftracker.coppersurfer.tk%3A6969&amp;tr=udp%3A%2F%2Fexodus.desync.com%3A6969","seeders":1,"leechers":0,"uploader":"Nepotu","files":1,"time":1360080697,"description":"Credit: K0cM0c","torrent":{"xt":"urn:btih:5498f1b24b1e416d0a241e0308f665462ac6ac62","amp;dn":"NHL.2013.RS.%2804+feb%29.MNN.Wild.v.PHX.Coyotes.540p","amp;tr":["udp%3A%2F%2Ftracker.openbittorrent.com%3A80","udp%3A%2F%2Fopen.demonii.com%3A1337","udp%3A%2F%2Ftracker.coppersurfer.tk%3A6969","udp%3A%2F%2Fexodus.desync.com%3A6969"],"infoHash":"5498f1b24b1e416d0a241e0308f665462ac6ac62","infoHashBuffer":{"type":"Buffer","data":[84,152,241,178,75,30,65,109,10,36,30,3,8,246,101,70,42,198,172,98]},"announce":[],"urlList":[]}}