{"title":"Diario ABC 10.03.15","uid":11744922,"size":37984144,"categoryP":"other","categoryS":"other","magnet":"?xt=urn:btih:555429300e13bb9e86927c1b1a3f2ec32e594566&amp;dn=Diario+ABC+10.03.15&amp;tr=udp%3A%2F%2Ftracker.openbittorrent.com%3A80&amp;tr=udp%3A%2F%2Fopen.demonii.com%3A1337&amp;tr=udp%3A%2F%2Ftracker.coppersurfer.tk%3A6969&amp;tr=udp%3A%2F%2Fexodus.desync.com%3A6969","seeders":1,"leechers":0,"uploader":"virana","files":1,"time":1425972708,"description":"abc","torrent":{"xt":"urn:btih:555429300e13bb9e86927c1b1a3f2ec32e594566","amp;dn":"Diario+ABC+10.03.15","amp;tr":["udp%3A%2F%2Ftracker.openbittorrent.com%3A80","udp%3A%2F%2Fopen.demonii.com%3A1337","udp%3A%2F%2Ftracker.coppersurfer.tk%3A6969","udp%3A%2F%2Fexodus.desync.com%3A6969"],"infoHash":"555429300e13bb9e86927c1b1a3f2ec32e594566","infoHashBuffer":{"type":"Buffer","data":[85,84,41,48,14,19,187,158,134,146,124,27,26,63,46,195,46,89,69,102]},"announce":[],"urlList":[]}}