{"title":"Mastering Windows XP Registry.pdf","uid":3951775,"size":3845996,"categoryP":"other","categoryS":"e_books","magnet":"?xt=urn:btih:59910f87a9a16ff006477619d0b5af36f3f72740&amp;dn=Mastering+Windows+XP+Registry.pdf&amp;tr=udp%3A%2F%2Ftracker.openbittorrent.com%3A80&amp;tr=udp%3A%2F%2Fopen.demonii.com%3A1337&amp;tr=udp%3A%2F%2Ftracker.coppersurfer.tk%3A6969&amp;tr=udp%3A%2F%2Fexodus.desync.com%3A6969","seeders":1,"leechers":0,"uploader":"Masterart","files":1,"time":1198903749,"description":"Mastering Windows XP Registry.pdf","torrent":{"xt":"urn:btih:59910f87a9a16ff006477619d0b5af36f3f72740","amp;dn":"Mastering+Windows+XP+Registry.pdf","amp;tr":["udp%3A%2F%2Ftracker.openbittorrent.com%3A80","udp%3A%2F%2Fopen.demonii.com%3A1337","udp%3A%2F%2Ftracker.coppersurfer.tk%3A6969","udp%3A%2F%2Fexodus.desync.com%3A6969"],"infoHash":"59910f87a9a16ff006477619d0b5af36f3f72740","infoHashBuffer":{"type":"Buffer","data":[89,145,15,135,169,161,111,240,6,71,118,25,208,181,175,54,243,247,39,64]},"announce":[],"urlList":[]}}