{"title":"The Rachel Maddow Show - 2013.02.22 - XviD","uid":8179609,"size":314605568,"categoryP":"video","categoryS":"tv_shows","magnet":"?xt=urn:btih:6e819043303135c388f3cb568940c027784a303c&amp;dn=The+Rachel+Maddow+Show+-+2013.02.22+-+XviD&amp;tr=udp%3A%2F%2Ftracker.openbittorrent.com%3A80&amp;tr=udp%3A%2F%2Fopen.demonii.com%3A1337&amp;tr=udp%3A%2F%2Ftracker.coppersurfer.tk%3A6969&amp;tr=udp%3A%2F%2Fexodus.desync.com%3A6969","seeders":1,"leechers":0,"uploader":null,"files":1,"time":1361598728,"description":"\nThe Rachel Maddow Show\nFebruary 22 - 2013\n\nGuest:\nJane Mayer - author, investigative journalist for The New Yorker \n\nSDTV\n43 Min \n640x400\n836 kbps\n29.97 fps\nXviD","torrent":{"xt":"urn:btih:6e819043303135c388f3cb568940c027784a303c","amp;dn":"The+Rachel+Maddow+Show+-+2013.02.22+-+XviD","amp;tr":["udp%3A%2F%2Ftracker.openbittorrent.com%3A80","udp%3A%2F%2Fopen.demonii.com%3A1337","udp%3A%2F%2Ftracker.coppersurfer.tk%3A6969","udp%3A%2F%2Fexodus.desync.com%3A6969"],"infoHash":"6e819043303135c388f3cb568940c027784a303c","infoHashBuffer":{"type":"Buffer","data":[110,129,144,67,48,49,53,195,136,243,203,86,137,64,192,39,120,74,48,60]},"announce":[],"urlList":[]}}