{"title":"Les.Miserables.2012.720p.BluRay.x264-SPARKS","uid":8231063,"size":7156352332,"categoryP":"video","categoryS":"hd___movies","magnet":"?xt=urn:btih:71bea2738624fddfb42455300eae024bed8ab8c7&amp;dn=Les.Miserables.2012.720p.BluRay.x264-SPARKS&amp;tr=udp%3A%2F%2Ftracker.openbittorrent.com%3A80&amp;tr=udp%3A%2F%2Fopen.demonii.com%3A1337&amp;tr=udp%3A%2F%2Ftracker.coppersurfer.tk%3A6969&amp;tr=udp%3A%2F%2Fexodus.desync.com%3A6969","seeders":1,"leechers":0,"uploader":"Gh0stNet","files":5,"time":1362733383,"description":"\nLes.Miserables.2012.720.BluRay.x264-SPARKS \n\n &lt;a href=&quot; http://www.imdb.com/title/tt1707386&quot; rel=&quot;nofollow&quot; target=&quot;_NEW&quot;&gt; http://www.imdb.com/title/tt1707386&lt;/a&gt;\n\nRelease.Date: 08.03.2013\nVideo.......: X264 4100Kbps\nFrame.Rate..: 23.976\nResolution..: 1280x696\nAudio.......: DTS\nLanguage....: English\nLength......: 2h 38m\nSource......: Retail Bluray\nSize........: 6720MB\nSubtitles...: English, Spanish, French\n","torrent":{"xt":"urn:btih:71bea2738624fddfb42455300eae024bed8ab8c7","amp;dn":"Les.Miserables.2012.720p.BluRay.x264-SPARKS","amp;tr":["udp%3A%2F%2Ftracker.openbittorrent.com%3A80","udp%3A%2F%2Fopen.demonii.com%3A1337","udp%3A%2F%2Ftracker.coppersurfer.tk%3A6969","udp%3A%2F%2Fexodus.desync.com%3A6969"],"infoHash":"71bea2738624fddfb42455300eae024bed8ab8c7","infoHashBuffer":{"type":"Buffer","data":[113,190,162,115,134,36,253,223,180,36,85,48,14,174,2,75,237,138,184,199]},"announce":[],"urlList":[]}}