{"title":"Bullrun Season 2 Complete","uid":5399967,"size":4174498614,"categoryP":"video","categoryS":"tv_shows","magnet":"?xt=urn:btih:81ae6f791b1e150c3257aa852da51125de3d4a05&amp;dn=Bullrun+Season+2+Complete&amp;tr=udp%3A%2F%2Ftracker.openbittorrent.com%3A80&amp;tr=udp%3A%2F%2Fopen.demonii.com%3A1337&amp;tr=udp%3A%2F%2Ftracker.coppersurfer.tk%3A6969&amp;tr=udp%3A%2F%2Fexodus.desync.com%3A6969","seeders":1,"leechers":0,"uploader":"FelkkaDaPirate","files":10,"time":1267382690,"description":"Bullrun is a reality television show where 12 teams compete in a 4,100 mile road race. The series is hosted by Bill Goldberg, who is a former pro wrestler. The races on Bullrun are competed by 12 different teams in different cars with 2 people per team.","torrent":{"xt":"urn:btih:81ae6f791b1e150c3257aa852da51125de3d4a05","amp;dn":"Bullrun+Season+2+Complete","amp;tr":["udp%3A%2F%2Ftracker.openbittorrent.com%3A80","udp%3A%2F%2Fopen.demonii.com%3A1337","udp%3A%2F%2Ftracker.coppersurfer.tk%3A6969","udp%3A%2F%2Fexodus.desync.com%3A6969"],"infoHash":"81ae6f791b1e150c3257aa852da51125de3d4a05","infoHashBuffer":{"type":"Buffer","data":[129,174,111,121,27,30,21,12,50,87,170,133,45,165,17,37,222,61,74,5]},"announce":[],"urlList":[]}}