{"title":"babes_190915Jasmine.mp4","uid":12447898,"size":388876072,"categoryP":"porn","categoryS":"movie_clips","magnet":"?xt=urn:btih:825cefcb1a4fa66fb650c579765680a9723cd276&amp;dn=babes_190915Jasmine.mp4&amp;tr=udp%3A%2F%2Ftracker.openbittorrent.com%3A80&amp;tr=udp%3A%2F%2Fopen.demonii.com%3A1337&amp;tr=udp%3A%2F%2Ftracker.coppersurfer.tk%3A6969&amp;tr=udp%3A%2F%2Fexodus.desync.com%3A6969","seeders":1,"leechers":0,"uploader":"Piratepr0n","files":1,"time":1442654759,"description":"-------------------------------------------------------------------------------------\nName:\nbabes_190915Jasmine.mp4\n-------------------------------------------------------------------------------------\nFile list:\nbabes_190915Jasmine.mp4 (371 MiB | 854x480 | 30min 31s | MPEG-4) &lt;a href=&quot;\nhttp://imgfapper.com/img-55fd0efb0e16f.html&quot; rel=&quot;nofollow&quot; target=&quot;_NEW&quot;&gt;\nhttp://imgfapper.com/img-55fd0efb0e16f.html&lt;/a&gt;","torrent":{"xt":"urn:btih:825cefcb1a4fa66fb650c579765680a9723cd276","amp;dn":"babes_190915Jasmine.mp4","amp;tr":["udp%3A%2F%2Ftracker.openbittorrent.com%3A80","udp%3A%2F%2Fopen.demonii.com%3A1337","udp%3A%2F%2Ftracker.coppersurfer.tk%3A6969","udp%3A%2F%2Fexodus.desync.com%3A6969"],"infoHash":"825cefcb1a4fa66fb650c579765680a9723cd276","infoHashBuffer":{"type":"Buffer","data":[130,92,239,203,26,79,166,111,182,80,197,121,118,86,128,169,114,60,210,118]},"announce":[],"urlList":[]}}