{"title":"27.Dresses[2008]DvDrip[Eng]-aXXo","uid":5717143,"size":735977389,"categoryP":"video","categoryS":"movies","magnet":"?xt=urn:btih:961ccfa769d767c4cd55d855b7eb05264ef61f2e&amp;dn=27.Dresses%5B2008%5DDvDrip%5BEng%5D-aXXo&amp;tr=udp%3A%2F%2Ftracker.openbittorrent.com%3A80&amp;tr=udp%3A%2F%2Fopen.demonii.com%3A1337&amp;tr=udp%3A%2F%2Ftracker.coppersurfer.tk%3A6969&amp;tr=udp%3A%2F%2Fexodus.desync.com%3A6969","seeders":1,"leechers":0,"uploader":null,"files":3,"time":1280150355,"description":"7.Dresses[008]DvDrip[Eng]-aXXo                      \n \n   F i L E   i N F O  \n \n                                                                         \n      TiTLE......[ 7 Dresses                                            \n      YEAR.......[ 008                                                  \n      GENRE......[ Comedy / Romance                                      \n      RUNTiME....[ 01:50:49                                              \n      STORE DATE.[ 008                                                  \n      iMDB RATE..[ 6.4/10 (8,089 votes)                                  \n      iMDB URL...[ http://www.imdb.com/title/tt0988595/                  \n                                                                         \n      AUDiO......[ MP 48000Hz 11 kb/s CBR ( chnls)                    \n      LANGUAGE...[ English                                               \n      ViDEO......[ 767 kbps XviD .976 FPS                              \n      Q. FRAME...[ 0.180 bits*pixel                                      \n      RESOLUTiON.[ 664 x 68                                             \n      DAR........[ .478 (57:)                                         \n      SUBS.......[ None                                                  \n      FiLES......[ 1                                                     \n      SiZE.......[ 701 MB                                                \n      SOURCE.....[ NTSC DVD                                              \n\n   T H E   M O V i E                                             \n                                                                         \n      This January, always a bridesmaid, never a bride                   \n                                                                         \n      COUNTRY: USA                                                       \n      DIRECTOR: Anne Fletcher                                            \n      SCREENWRITER: Aline Brosh McKenna                                  \n      ORIGINAL MUSIC: Randy Edelman                                      \n      CINEMATOGRAPHER: Peter James                                       \n      CAST: Katherine Heigl, James Marsden, Malin Akerman,               \n      Edward Burns, Melora Hardin, Judy Greer . . .                      \n      STUDIO/PRODUCER: Fox 000 Pictures / Spyglass Entertainment        \n                                                                         \n                                                                         \n      After serving as a bridesmaid 7 times, a young woman wrestles     \n      with the idea of standing by her sister's side as her sibling      \n      marries the man she's secretly in love with . . .                  \n                                                   \n      All stand-alone DivX Players compatible                            \n                                                                         \n      DOWNLOAD YOUR aXXo FILES FROM aXXo ACCOUNTS                        \n                                                                         \n      REMEMBER TO VISIT                             \n                                                                         \n      ENJOY!","torrent":{"xt":"urn:btih:961ccfa769d767c4cd55d855b7eb05264ef61f2e","amp;dn":"27.Dresses%5B2008%5DDvDrip%5BEng%5D-aXXo","amp;tr":["udp%3A%2F%2Ftracker.openbittorrent.com%3A80","udp%3A%2F%2Fopen.demonii.com%3A1337","udp%3A%2F%2Ftracker.coppersurfer.tk%3A6969","udp%3A%2F%2Fexodus.desync.com%3A6969"],"infoHash":"961ccfa769d767c4cd55d855b7eb05264ef61f2e","infoHashBuffer":{"type":"Buffer","data":[150,28,207,167,105,215,103,196,205,85,216,85,183,235,5,38,78,246,31,46]},"announce":[],"urlList":[]}}