{"title":"Falling Skies [HDTV][3x01-02][Español]","uid":8589723,"size":968267776,"categoryP":"video","categoryS":"movies","magnet":"?xt=urn:btih:98af003aad4ce96ca0e50b50e776b0991debc28d&amp;dn=Falling+Skies+%5BHDTV%5D%5B3x01-02%5D%5BEspa%26ntilde%3Bol%5D&amp;tr=udp%3A%2F%2Ftracker.openbittorrent.com%3A80&amp;tr=udp%3A%2F%2Fopen.demonii.com%3A1337&amp;tr=udp%3A%2F%2Ftracker.coppersurfer.tk%3A6969&amp;tr=udp%3A%2F%2Fexodus.desync.com%3A6969","seeders":1,"leechers":0,"uploader":"espi91","files":-1,"time":1371607997,"description":"Narra la historia de la invasion de la Tierra por parte de unos agresivos alienigenas que quieren exterminar a los seres humanos Tom Mason es un antiguo profesor de Historia de una universidad de Boston cuya familia ha quedado destrozada por la invasion Su esposa murio durante el primer ataque y uno de sus tres hijos fue capturado Decidido a rescatarlo y a mantener a los otros dos a salvo Tom tendra que poner a prueba sus conocimientos de historia militar","torrent":{"xt":"urn:btih:98af003aad4ce96ca0e50b50e776b0991debc28d","amp;dn":"Falling+Skies+%5BHDTV%5D%5B3x01-02%5D%5BEspa%26ntilde%3Bol%5D","amp;tr":["udp%3A%2F%2Ftracker.openbittorrent.com%3A80","udp%3A%2F%2Fopen.demonii.com%3A1337","udp%3A%2F%2Ftracker.coppersurfer.tk%3A6969","udp%3A%2F%2Fexodus.desync.com%3A6969"],"infoHash":"98af003aad4ce96ca0e50b50e776b0991debc28d","infoHashBuffer":{"type":"Buffer","data":[152,175,0,58,173,76,233,108,160,229,11,80,231,118,176,153,29,235,194,141]},"announce":[],"urlList":[]}}