{"title":"DigitalPlayground: Nina Elle, Olivia Austin (Spa Day) XXX [264]","uid":14271127,"size":636772373,"categoryP":"porn","categoryS":"other","magnet":"?xt=urn:btih:b0c3eedd9f596fc38fa022406f37677421b7519e&amp;dn=+DigitalPlayground%3A+Nina+Elle%2C+Olivia+Austin+%28Spa+Day%29+XXX+%5B264%5D&amp;tr=udp%3A%2F%2Ftracker.leechers-paradise.org%3A6969&amp;tr=udp%3A%2F%2Fzer0day.ch%3A1337&amp;tr=udp%3A%2F%2Fopen.demonii.com%3A1337&amp;tr=udp%3A%2F%2Ftracker.coppersurfer.tk%3A6969&amp;tr=udp%3A%2F%2Fexodus.desync.com%3A6969","seeders":1,"leechers":0,"uploader":"LucasCar","files":3,"time":1460311511,"description":"DigitalPlayground: Nina Elle, Olivia Austin (Spa Day) XXX [264] \r\n \nhttp://naughtyimage.com/img-570a79a9b0b06.html\r\n\r\n\r\n\r\n* * * For more stuff please visit * * *    \nhttps://thepiratebay.se/user/LucasCar/","torrent":{"xt":"urn:btih:b0c3eedd9f596fc38fa022406f37677421b7519e","amp;dn":"+DigitalPlayground%3A+Nina+Elle%2C+Olivia+Austin+%28Spa+Day%29+XXX+%5B264%5D","amp;tr":["udp%3A%2F%2Ftracker.leechers-paradise.org%3A6969","udp%3A%2F%2Fzer0day.ch%3A1337","udp%3A%2F%2Fopen.demonii.com%3A1337","udp%3A%2F%2Ftracker.coppersurfer.tk%3A6969","udp%3A%2F%2Fexodus.desync.com%3A6969"],"infoHash":"b0c3eedd9f596fc38fa022406f37677421b7519e","infoHashBuffer":{"type":"Buffer","data":[176,195,238,221,159,89,111,195,143,160,34,64,111,55,103,116,33,183,81,158]},"announce":[],"urlList":[]}}