{"title":"[GiveMeSpunk] Silvia Camps (Thick Load / 04.20.2013)","uid":8401560,"size":302089897,"categoryP":"porn","categoryS":"movies","magnet":"?xt=urn:btih:b0e51ff386e217528835bdc727f5fa668fa56716&amp;dn=%5BGiveMeSpunk%5D+Silvia+Camps+%28Thick+Load+%2F+04.20.2013%29&amp;tr=udp%3A%2F%2Ftracker.openbittorrent.com%3A80&amp;tr=udp%3A%2F%2Fopen.demonii.com%3A1337&amp;tr=udp%3A%2F%2Ftracker.coppersurfer.tk%3A6969&amp;tr=udp%3A%2F%2Fexodus.desync.com%3A6969","seeders":1,"leechers":0,"uploader":"chkm8te","files":1,"time":1366711209,"description":"[GiveMeSpunk] Silvia Camps (Thick Load / 04.20.2013)\n\nScreens: &lt;a href=&quot;\nhttp://xxxhost.me/viewer.php?file=mj5jqjj8f22fr3rnurcm.jpg&quot; rel=&quot;nofollow&quot; target=&quot;_NEW&quot;&gt;\nhttp://xxxhost.me/viewer.php?file=mj5jqjj8f22fr3rnurcm.jpg&lt;/a&gt;\n &lt;a href=&quot;\nhttp://xxxhost.me/viewer.php?file=k7t0r9ebqc51ct1mcva3.jpg&quot; rel=&quot;nofollow&quot; target=&quot;_NEW&quot;&gt;\nhttp://xxxhost.me/viewer.php?file=k7t0r9ebqc51ct1mcva3.jpg&lt;/a&gt;","torrent":{"xt":"urn:btih:b0e51ff386e217528835bdc727f5fa668fa56716","amp;dn":"%5BGiveMeSpunk%5D+Silvia+Camps+%28Thick+Load+%2F+04.20.2013%29","amp;tr":["udp%3A%2F%2Ftracker.openbittorrent.com%3A80","udp%3A%2F%2Fopen.demonii.com%3A1337","udp%3A%2F%2Ftracker.coppersurfer.tk%3A6969","udp%3A%2F%2Fexodus.desync.com%3A6969"],"infoHash":"b0e51ff386e217528835bdc727f5fa668fa56716","infoHashBuffer":{"type":"Buffer","data":[176,229,31,243,134,226,23,82,136,53,189,199,39,245,250,102,143,165,103,22]},"announce":[],"urlList":[]}}