{"title":"Braindead 1x08 (720p-HDTV-x264-DIMENSION)[VTV]","uid":15568796,"size":850865779,"categoryP":"video","categoryS":"hd___tv_shows","magnet":"?xt=urn:btih:b3c073eb00810995e6a3ccad8b61fd0439147026&amp;dn=Braindead+1x08+%28720p-HDTV-x264-DIMENSION%29%5BVTV%5D&amp;tr=udp%3A%2F%2Ftracker.leechers-paradise.org%3A6969&amp;tr=udp%3A%2F%2Fzer0day.ch%3A1337&amp;tr=udp%3A%2F%2Fopen.demonii.com%3A1337&amp;tr=udp%3A%2F%2Ftracker.coppersurfer.tk%3A6969&amp;tr=udp%3A%2F%2Fexodus.desync.com%3A6969","seeders":1,"leechers":1,"uploader":"realVTV","files":1,"time":1471234026,"description":"Braindead 1x08 (720p-HDTV-x264-DIMENSION)[VTV]","torrent":{"xt":"urn:btih:b3c073eb00810995e6a3ccad8b61fd0439147026","amp;dn":"Braindead+1x08+%28720p-HDTV-x264-DIMENSION%29%5BVTV%5D","amp;tr":["udp%3A%2F%2Ftracker.leechers-paradise.org%3A6969","udp%3A%2F%2Fzer0day.ch%3A1337","udp%3A%2F%2Fopen.demonii.com%3A1337","udp%3A%2F%2Ftracker.coppersurfer.tk%3A6969","udp%3A%2F%2Fexodus.desync.com%3A6969"],"infoHash":"b3c073eb00810995e6a3ccad8b61fd0439147026","infoHashBuffer":{"type":"Buffer","data":[179,192,115,235,0,129,9,149,230,163,204,173,139,97,253,4,57,20,112,38]},"announce":[],"urlList":[]}}