{"title":"NCIS S09E14 HDTV - NL Subs - StRaLa","uid":7026075,"size":366858575,"categoryP":"video","categoryS":"tv_shows","magnet":"?xt=urn:btih:b60bbf23868160616546a6807cc06203a51b105e&amp;dn=NCIS+S09E14+HDTV+-+NL+Subs+-+StRaLa&amp;tr=udp%3A%2F%2Ftracker.openbittorrent.com%3A80&amp;tr=udp%3A%2F%2Fopen.demonii.com%3A1337&amp;tr=udp%3A%2F%2Ftracker.coppersurfer.tk%3A6969&amp;tr=udp%3A%2F%2Fexodus.desync.com%3A6969","seeders":1,"leechers":0,"uploader":"St-Ra-La","files":-1,"time":1329004621,"description":"\nNCIS - S09E14\n\nIMDB: &lt;a href=&quot; http://www.imdb.com/title/tt0364845/&quot; rel=&quot;nofollow&quot; target=&quot;_NEW&quot;&gt; http://www.imdb.com/title/tt0364845/&lt;/a&gt;\n\nCategorie: TV Serie\n\nFormat: AVI (XVID)\n\nVideo: MPEG-4 Visual\nAspect: 624 x 352\n\nAudio: English, MPEG Audio (MP3)\nInfos: 2 (ch) kanalen, Stereo, 48,0 KHz\n\nDutch ( NL )Hardcoded Subs!\n\nEnjoy,\nStRaLa\n","torrent":{"xt":"urn:btih:b60bbf23868160616546a6807cc06203a51b105e","amp;dn":"NCIS+S09E14+HDTV+-+NL+Subs+-+StRaLa","amp;tr":["udp%3A%2F%2Ftracker.openbittorrent.com%3A80","udp%3A%2F%2Fopen.demonii.com%3A1337","udp%3A%2F%2Ftracker.coppersurfer.tk%3A6969","udp%3A%2F%2Fexodus.desync.com%3A6969"],"infoHash":"b60bbf23868160616546a6807cc06203a51b105e","infoHashBuffer":{"type":"Buffer","data":[182,11,191,35,134,129,96,97,101,70,166,128,124,192,98,3,165,27,16,94]},"announce":[],"urlList":[]}}