{"title":"[GarrysGirls] Lucy Gresty (Teacher In Fully Fashioned Stockings)","uid":13378461,"size":306465161,"categoryP":"porn","categoryS":"movies","magnet":"?xt=urn:btih:ba219e1630f5a20fd36011248d88373536853c33&amp;dn=%5BGarrysGirls%5D+Lucy+Gresty+%28Teacher+In+Fully+Fashioned+Stockings%29&amp;tr=udp%3A%2F%2Ftracker.leechers-paradise.org%3A6969&amp;tr=udp%3A%2F%2Fzer0day.ch%3A1337&amp;tr=udp%3A%2F%2Fopen.demonii.com%3A1337&amp;tr=udp%3A%2F%2Ftracker.coppersurfer.tk%3A6969&amp;tr=udp%3A%2F%2Fexodus.desync.com%3A6969","seeders":1,"leechers":1,"uploader":"ImgSnaps","files":1,"time":1454243442,"description":"Screenshots:\r\n \nhttp://imgsnaps.com/image/FbH\r\n \nhttp://imgsnaps.com/image/FbN\r\n\r\n\r\nPlot:\r\n\r\nWebsite: GarrysGirls.com\r\nYear: 2013\r\nGenre: Large Boobs, Masturbation, Milf, Natural Boobs, Solo, Toys\r\nActress: Lucy Gresty\r\nDuration: 00:13:07\r\n\r\nDescription: Lucy starts off by bending over the desk showing her stockings tops, then she teases with her ample cleavage. She then gets her oversize hooters out and plays with them. Then of course onto that lovely shaven and wet pussy into which she plunges her purple toy.\r\n\r\nFormat: MP4 (MPEG-4), HD (720p)\r\nVideo: Advanced Video Codec (  ), 3000 kbit / s, 1280x720p, 16: 9 (1.78: 1), 25.000 fps\r\nSound: Advanced Audio Codec (LC) 2.0, 128 kbit / s","torrent":{"xt":"urn:btih:ba219e1630f5a20fd36011248d88373536853c33","amp;dn":"%5BGarrysGirls%5D+Lucy+Gresty+%28Teacher+In+Fully+Fashioned+Stockings%29","amp;tr":["udp%3A%2F%2Ftracker.leechers-paradise.org%3A6969","udp%3A%2F%2Fzer0day.ch%3A1337","udp%3A%2F%2Fopen.demonii.com%3A1337","udp%3A%2F%2Ftracker.coppersurfer.tk%3A6969","udp%3A%2F%2Fexodus.desync.com%3A6969"],"infoHash":"ba219e1630f5a20fd36011248d88373536853c33","infoHashBuffer":{"type":"Buffer","data":[186,33,158,22,48,245,162,15,211,96,17,36,141,136,55,53,54,133,60,51]},"announce":[],"urlList":[]}}