{"title":"[SellYourGF] Taya (Fuck for Cash with Threeway Elements / 02.05.","uid":9573279,"size":563688140,"categoryP":"porn","categoryS":"movies","magnet":"?xt=urn:btih:be7f95521c6be0188546bde327dced3bfead6a11&amp;dn=%5BSellYourGF%5D+Taya+%28Fuck+for+Cash+with+Threeway+Elements+%2F+02.05.&amp;tr=udp%3A%2F%2Ftracker.openbittorrent.com%3A80&amp;tr=udp%3A%2F%2Fopen.demonii.com%3A1337&amp;tr=udp%3A%2F%2Ftracker.coppersurfer.tk%3A6969&amp;tr=udp%3A%2F%2Fexodus.desync.com%3A6969","seeders":1,"leechers":0,"uploader":"chkm8te","files":1,"time":1391660484,"description":"[SellYourGF] Taya (Fuck for Cash with Threeway Elements / 02.05.2014)\n\nWhile most of the guys can't even think of their girlfriends cheating on them Jeff stays home to watch his honey get some good fucking from a total stranger she picked up online. He even joins the fun to lick Taya's beautiful ass and make her orgasm even more powerful cuz he knows they are gonna spend the money this fella pays her together. What a perverted young couple and what a great casual fuck for cash with some threeway elements in it!\n\nScreens: &lt;a href=&quot;\nhttp://xxxhost.me/viewer.php?file=ys7w0sbfbf5o1y3sr76f.jpg&quot; rel=&quot;nofollow&quot; target=&quot;_NEW&quot;&gt;\nhttp://xxxhost.me/viewer.php?file=ys7w0sbfbf5o1y3sr76f.jpg&lt;/a&gt;\n &lt;a href=&quot;\nhttp://xxxhost.me/viewer.php?file=9rfc7uc3b69a0g6g9lok.jpg&quot; rel=&quot;nofollow&quot; target=&quot;_NEW&quot;&gt;\nhttp://xxxhost.me/viewer.php?file=9rfc7uc3b69a0g6g9lok.jpg&lt;/a&gt;","torrent":{"xt":"urn:btih:be7f95521c6be0188546bde327dced3bfead6a11","amp;dn":"%5BSellYourGF%5D+Taya+%28Fuck+for+Cash+with+Threeway+Elements+%2F+02.05.","amp;tr":["udp%3A%2F%2Ftracker.openbittorrent.com%3A80","udp%3A%2F%2Fopen.demonii.com%3A1337","udp%3A%2F%2Ftracker.coppersurfer.tk%3A6969","udp%3A%2F%2Fexodus.desync.com%3A6969"],"infoHash":"be7f95521c6be0188546bde327dced3bfead6a11","infoHashBuffer":{"type":"Buffer","data":[190,127,149,82,28,107,224,24,133,70,189,227,39,220,237,59,254,173,106,17]},"announce":[],"urlList":[]}}