{"title":"What really happens in Bali s01e03.pdtv.x264-w4f","uid":10337434,"size":430549254,"categoryP":"video","categoryS":"tv_shows","magnet":"?xt=urn:btih:c6e7830fd0cbe2fdd643df27b2cf3b5c2c8fabf1&amp;dn=What+really+happens+in+Bali+s01e03.pdtv.x264-w4f&amp;tr=udp%3A%2F%2Ftracker.openbittorrent.com%3A80&amp;tr=udp%3A%2F%2Fopen.demonii.com%3A1337&amp;tr=udp%3A%2F%2Ftracker.coppersurfer.tk%3A6969&amp;tr=udp%3A%2F%2Fexodus.desync.com%3A6969","seeders":1,"leechers":1,"uploader":"chrislv","files":1,"time":1402495253,"description":"Three mates are on holiday in Bali and come across Buffalo racing. A king hit on the streets leaves a life hanging in the balance and NYE fireworks sends two girls to the hospital.","torrent":{"xt":"urn:btih:c6e7830fd0cbe2fdd643df27b2cf3b5c2c8fabf1","amp;dn":"What+really+happens+in+Bali+s01e03.pdtv.x264-w4f","amp;tr":["udp%3A%2F%2Ftracker.openbittorrent.com%3A80","udp%3A%2F%2Fopen.demonii.com%3A1337","udp%3A%2F%2Ftracker.coppersurfer.tk%3A6969","udp%3A%2F%2Fexodus.desync.com%3A6969"],"infoHash":"c6e7830fd0cbe2fdd643df27b2cf3b5c2c8fabf1","infoHashBuffer":{"type":"Buffer","data":[198,231,131,15,208,203,226,253,214,67,223,39,178,207,59,92,44,143,171,241]},"announce":[],"urlList":[]}}