{"title":"CzechMassage 16 01 11 Massage 211 XXX 1080p MP4-KTR","uid":13196188,"size":344932346,"categoryP":"porn","categoryS":"movie_clips","magnet":"?xt=urn:btih:d05a28e2298f8422e189c6807ad0512d7eb9f199&amp;dn=CzechMassage+16+01+11+Massage+211+XXX+1080p+MP4-KTR&amp;tr=udp%3A%2F%2Ftracker.leechers-paradise.org%3A6969&amp;tr=udp%3A%2F%2Fzer0day.ch%3A1337&amp;tr=udp%3A%2F%2Fopen.demonii.com%3A1337&amp;tr=udp%3A%2F%2Ftracker.coppersurfer.tk%3A6969&amp;tr=udp%3A%2F%2Fexodus.desync.com%3A6969","seeders":1,"leechers":2,"uploader":"0-DayXXX","files":1,"time":1452486402,"description":"------------------------------------------------\r\nCzechMassage 16 01 11 Massage 211 XXX 1080p MP4-KTR\r\n------------------------------------------------\r\nScreenshot(s):  \nhttp://youpornbook.com/forums/topic/4597-czechmassage-16-01-11-massage-211-xxx-1080p-mp4-ktr/\r\n\r\n------------------------------------------------\r\n         ** More 0-DayXXX Uploads **  \nhttp://youpornbook.com/forums/forum/18-0day/\r\n------------------------------------------------\r\nIf you like this torrent, please post a comment!\r\n            Don't forget to seed!","torrent":{"xt":"urn:btih:d05a28e2298f8422e189c6807ad0512d7eb9f199","amp;dn":"CzechMassage+16+01+11+Massage+211+XXX+1080p+MP4-KTR","amp;tr":["udp%3A%2F%2Ftracker.leechers-paradise.org%3A6969","udp%3A%2F%2Fzer0day.ch%3A1337","udp%3A%2F%2Fopen.demonii.com%3A1337","udp%3A%2F%2Ftracker.coppersurfer.tk%3A6969","udp%3A%2F%2Fexodus.desync.com%3A6969"],"infoHash":"d05a28e2298f8422e189c6807ad0512d7eb9f199","infoHashBuffer":{"type":"Buffer","data":[208,90,40,226,41,143,132,34,225,137,198,128,122,208,81,45,126,185,241,153]},"announce":[],"urlList":[]}}