{"title":"Revista Interviu 20-1-2013","uid":8042647,"size":44592908,"categoryP":"porn","categoryS":"other","magnet":"?xt=urn:btih:d3462a593338f5d08bc2a539eee43332f8b1073c&amp;dn=Revista+Interviu+20-1-2013&amp;tr=udp%3A%2F%2Ftracker.openbittorrent.com%3A80&amp;tr=udp%3A%2F%2Fopen.demonii.com%3A1337&amp;tr=udp%3A%2F%2Ftracker.coppersurfer.tk%3A6969&amp;tr=udp%3A%2F%2Fexodus.desync.com%3A6969","seeders":1,"leechers":0,"uploader":"furtaperas","files":-1,"time":1358675184,"description":"revista interviu ","torrent":{"xt":"urn:btih:d3462a593338f5d08bc2a539eee43332f8b1073c","amp;dn":"Revista+Interviu+20-1-2013","amp;tr":["udp%3A%2F%2Ftracker.openbittorrent.com%3A80","udp%3A%2F%2Fopen.demonii.com%3A1337","udp%3A%2F%2Ftracker.coppersurfer.tk%3A6969","udp%3A%2F%2Fexodus.desync.com%3A6969"],"infoHash":"d3462a593338f5d08bc2a539eee43332f8b1073c","infoHashBuffer":{"type":"Buffer","data":[211,70,42,89,51,56,245,208,139,194,165,57,238,228,51,50,248,177,7,60]},"announce":[],"urlList":[]}}