{"title":"The.Beat.That.My.Heart.Skipped.2005.BluRay.720p.DTS.x264-CHD [Pu","uid":9065625,"size":5373327061,"categoryP":"video","categoryS":"hd___movies","magnet":"?xt=urn:btih:e1d259424129f6ec9bc11ae4f976376da9327429&amp;dn=The.Beat.That.My.Heart.Skipped.2005.BluRay.720p.DTS.x264-CHD+%5BPu&amp;tr=udp%3A%2F%2Ftracker.openbittorrent.com%3A80&amp;tr=udp%3A%2F%2Fopen.demonii.com%3A1337&amp;tr=udp%3A%2F%2Ftracker.coppersurfer.tk%3A6969&amp;tr=udp%3A%2F%2Fexodus.desync.com%3A6969","seeders":1,"leechers":2,"uploader":"aoloffline","files":-1,"time":1382108103,"description":"\n                PublicHD - High-Definition Bittorrent Community\n      \n              ----------------------------------------------------\n\nThe.Beat.That.My.Heart.Skipped.2005.BluRay.720p.DTS.x264-CHD [PublicHD]\n &lt;a href=&quot;\nhttp://www.imdb.com/title/tt0411270/&quot; rel=&quot;nofollow&quot; target=&quot;_NEW&quot;&gt;\nhttp://www.imdb.com/title/tt0411270/&lt;/a&gt;\n\nLength..............: 1h 46mn\nVideo...............: 1280x690 (X264 @ 24.000fps)\nBitrate.............: 6725Kbps\nAudio...............: DTS 1509 Kbps\nLanguage............: French / English / Russian / Vietnamese / Mandarin\nSubtitles...........: N/A\nGenre ..............:  | Action\n\n\nS C R E E N S :\n &lt;a href=&quot;\nhttp://someimage.com/QEdgFIN&quot; rel=&quot;nofollow&quot; target=&quot;_NEW&quot;&gt;\nhttp://someimage.com/QEdgFIN&lt;/a&gt;\n &lt;a href=&quot;\nhttp://someimage.com/I4DtPqn&quot; rel=&quot;nofollow&quot; target=&quot;_NEW&quot;&gt;\nhttp://someimage.com/I4DtPqn&lt;/a&gt;\n &lt;a href=&quot;\nhttp://someimage.com/taeEPGP&quot; rel=&quot;nofollow&quot; target=&quot;_NEW&quot;&gt;\nhttp://someimage.com/taeEPGP&lt;/a&gt;\n &lt;a href=&quot;\nhttp://someimage.com/ydpIafc&quot; rel=&quot;nofollow&quot; target=&quot;_NEW&quot;&gt;\nhttp://someimage.com/ydpIafc&lt;/a&gt;\n &lt;a href=&quot;\nhttp://someimage.com/3bxQ7dE&quot; rel=&quot;nofollow&quot; target=&quot;_NEW&quot;&gt;\nhttp://someimage.com/3bxQ7dE&lt;/a&gt;\n\n\n","torrent":{"xt":"urn:btih:e1d259424129f6ec9bc11ae4f976376da9327429","amp;dn":"The.Beat.That.My.Heart.Skipped.2005.BluRay.720p.DTS.x264-CHD+%5BPu","amp;tr":["udp%3A%2F%2Ftracker.openbittorrent.com%3A80","udp%3A%2F%2Fopen.demonii.com%3A1337","udp%3A%2F%2Ftracker.coppersurfer.tk%3A6969","udp%3A%2F%2Fexodus.desync.com%3A6969"],"infoHash":"e1d259424129f6ec9bc11ae4f976376da9327429","infoHashBuffer":{"type":"Buffer","data":[225,210,89,66,65,41,246,236,155,193,26,228,249,118,55,109,169,50,116,41]},"announce":[],"urlList":[]}}