{"title":"Death Race 1 (2008) &amp; 2 (2010) DVDrip x264 - RebourneD","uid":6083735,"size":677042599,"categoryP":"video","categoryS":"movies","magnet":"?xt=urn:btih:e5352676eee1882243f6ba0e8c104438b16fe57e&amp;dn=Death+Race+1+%282008%29+%26+2+%282010%29+DVDrip+x264+-+RebourneD&amp;tr=udp%3A%2F%2Ftracker.openbittorrent.com%3A80&amp;tr=udp%3A%2F%2Fopen.demonii.com%3A1337&amp;tr=udp%3A%2F%2Ftracker.coppersurfer.tk%3A6969&amp;tr=udp%3A%2F%2Fexodus.desync.com%3A6969","seeders":1,"leechers":0,"uploader":"RebourneD","files":4,"time":1294227341,"description":"xxxxxxxxxxxxxxxxxxxxxxxx\nDeath Race -Unrated Edition (2008)\nxxxxxxxxxxxxxxxxxxxxxxxx\n\nSource = DVD\n\n[img]http://upload.wikimedia.org/wikipedia/en/d/d2/Death_race_poster.jpg[/img]\n\nIMDB Info = [url]http://www.imdb.com/title/tt0452608/[/url]\n\nIMDB Rating = 6.6 out of 10\n\nTrailer =\n\n\nxxxxxxxxxxxxxxx\nSummary\\Plot\nxxxxxxxxxxxxxxx\n\nEx-con Jensen Ames is forced by the warden of a notorious prison to compete in our post-industrial world's most popular sport: a car race in which inmates must brutalize and kill one another on the road to victory. \n\nxxxxxxxxxxxxxxxxxxxxxxxxxxxxxxxxx\nCast, Crew and Additional Info\nxxxxxxxxxxxxxxxxxxxxxxxxxxxxxxxxx\n\nDirected by \tPaul W. S. Anderson\nProduced by \tPaul W. S. Anderson, Jeremy Bolt, Roger Corman, Paula Wagner\nScreenplay by \tPaul W. S. Anderson, Robert Thom (1975 screenplay), Charles Griffith (1975 screenplay)\nStory by \tPaul W. S. Anderson, Ib Melchior (1975 story)\n\nStarring\nxxxxxxxx\nJason Statham\nJoan Allen\nTyrese Gibson\nIan McShane\nNatalie Martinez\n\nMusic by \tPaul Haslinger\nStudio \tRelativity Media, Cruise/Wagner Productions, Impact Pictures\nDistributed by \tUniversal Pictures\n\nRelease date(s) \tAugust 22, 2008 (2008-08-22) (United States and Canada), September 26, 2008 (United Kingdom), October 30, 2008 (Australia)\nRunning time \t98 minutes\nCountry \tUnited States, Germany, United Kingdom\nLanguage \tEnglish\nBudget \t$45 million\nGross revenue \t$75,677,515\n\nx x x x x x x x x x x x x x x x x x x x x x x x x x x x x x x x x x x x\nCheck .nfo Included for File Properties and info.\nx x x x x x x x x x x x x x x x x x x x x x x x x x x x x x x x x x x x\n\nScreens\nxxxxxxxx\n[url]http://img560.imageshack.us/slideshow/webplayer.php?id=deathrace2008unratededi.jpg[/url]\n.....................................................................................\n\nxxxxxxxxxxxxxxxxxxxxxxxx\nDeath Race 2 (2010)\nxxxxxxxxxxxxxxxxxxxxxxxx\n\nSource = DVD\n\n[img]http://upload.wikimedia.org/wikipedia/en/c/c6/Death_Race_2_poster.jpg[/img]\n\nIMDB Info = [url]http://www.imdb.com/title/tt1500491/[/url]\n\nIMDB Rating = 5.6 out of 10\n\nTrailer =\n\n\nxxxxxxxxxxxxxxx\nSummary\\Plot\nxxxxxxxxxxxxxxx\n\nIn 2012, private corporations own and manage the prison systems. Getaway driver Carl &quot;Luke&quot; Lucas (Luke Goss) is arrested after a robbery for his crime boss Markus Kane (Sean Bean) goes wrong. As his accomplices are robbing the bank, two officers casually enter the building. Luke shoots and kills one of the officers and dumps off his accomplices in order to fulfill Markus's wishes. In doing so, Luke is eventually captured by the police following a high-speed chase and sentenced to serve time on Terminal Island. \n-An origin story for convicted cop killer Frankenstein.  \n\nxxxxxxxxxxxxxxxxxxxxxxxxxxxxxxxxx\nCast, Crew and Additional Info\nxxxxxxxxxxxxxxxxxxxxxxxxxxxxxxxxx\n\nDirected by \tRoel ReinÃƒÂ©\nProduced by \tPaul W. S. Anderson, Jeremy Bolt, Mike Elliott\nScreenplay by \tTony Giglio\nStory by \tPaul W. S. Anderson, Tony Giglio\n\nStarring\nxxxxxxxx\nLuke Goss\nTanit Phoenix\nDanny Trejo\nLauren Cohan\nRobin Shou\nVing Rhames\nSean Bean\n\nCinematography \tScott Kevan\nEditing by \tRadu Ion, Herman P. Koerts\nStudio \tMoonlighting Films\nDistributed by \tUniversal Studios, Paramount Pictures\n\nRelease date(s) \t18 January 2011\nRunning time \t96 min.\nCountry \tSouth Africa, Germany, New Zealand\nLanguage \tEnglish\nBudget \t$14 million\n\nx x x x x x x x x x x x x x x x x x x x x x x x x x x x x x x x x x x x\nCheck .nfo Included for File Properties and info.\nx x x x x x x x x x x x x x x x x x x x x x x x x x x x x x x x x x x x\n\nScreens\nxxxxxxxx\n[url]http://img560.imageshack.us/slideshow/webplayer.php?id=deathrace2008unratededi.jpg[/url]\n.....................................................................................\n\n\n-RebourneD\n-Team UltimA","torrent":{"xt":"urn:btih:e5352676eee1882243f6ba0e8c104438b16fe57e","amp;dn":"Death+Race+1+%282008%29+%26+2+%282010%29+DVDrip+x264+-+RebourneD","amp;tr":["udp%3A%2F%2Ftracker.openbittorrent.com%3A80","udp%3A%2F%2Fopen.demonii.com%3A1337","udp%3A%2F%2Ftracker.coppersurfer.tk%3A6969","udp%3A%2F%2Fexodus.desync.com%3A6969"],"infoHash":"e5352676eee1882243f6ba0e8c104438b16fe57e","infoHashBuffer":{"type":"Buffer","data":[229,53,38,118,238,225,136,34,67,246,186,14,140,16,68,56,177,111,229,126]},"announce":[],"urlList":[]}}