{"title":"[Evilangel] Lea Lexis, Stoya, Sandra Romain (Can I Offer You Som","uid":9279129,"size":589464411,"categoryP":"porn","categoryS":"movie_clips","magnet":"?xt=urn:btih:e65a67fbe6d70ec5fc576384198ace3807c8592a&amp;dn=%5BEvilangel%5D+Lea+Lexis%2C+Stoya%2C+Sandra+Romain+%28Can+I+Offer+You+Som&amp;tr=udp%3A%2F%2Ftracker.openbittorrent.com%3A80&amp;tr=udp%3A%2F%2Fopen.demonii.com%3A1337&amp;tr=udp%3A%2F%2Ftracker.coppersurfer.tk%3A6969&amp;tr=udp%3A%2F%2Fexodus.desync.com%3A6969","seeders":1,"leechers":1,"uploader":"chkm8te","files":2,"time":1385909243,"description":"[Evilangel] Lea Lexis, Stoya, Sandra Romain (Can I Offer You Something To Eat? / 11.27.2013)\n\nScreens:  &lt;a href=&quot;\nhttp://xxxhost.me/viewer.php?file=crfa6yqcw3wq9t2j2ygq.jpg&quot; rel=&quot;nofollow&quot; target=&quot;_NEW&quot;&gt;\nhttp://xxxhost.me/viewer.php?file=crfa6yqcw3wq9t2j2ygq.jpg&lt;/a&gt;\n  &lt;a href=&quot;\nhttp://xxxhost.me/viewer.php?file=bv8323zngoe7izxj0ec6.jpg&quot; rel=&quot;nofollow&quot; target=&quot;_NEW&quot;&gt;\nhttp://xxxhost.me/viewer.php?file=bv8323zngoe7izxj0ec6.jpg&lt;/a&gt;","torrent":{"xt":"urn:btih:e65a67fbe6d70ec5fc576384198ace3807c8592a","amp;dn":"%5BEvilangel%5D+Lea+Lexis%2C+Stoya%2C+Sandra+Romain+%28Can+I+Offer+You+Som","amp;tr":["udp%3A%2F%2Ftracker.openbittorrent.com%3A80","udp%3A%2F%2Fopen.demonii.com%3A1337","udp%3A%2F%2Ftracker.coppersurfer.tk%3A6969","udp%3A%2F%2Fexodus.desync.com%3A6969"],"infoHash":"e65a67fbe6d70ec5fc576384198ace3807c8592a","infoHashBuffer":{"type":"Buffer","data":[230,90,103,251,230,215,14,197,252,87,99,132,25,138,206,56,7,200,89,42]},"announce":[],"urlList":[]}}