{"title":"Sun Tzu - The Art of War","uid":5592471,"size":1442711,"categoryP":"other","categoryS":"e_books","magnet":"?xt=urn:btih:e8bd90f8227870d7a1644f4b4255ca54f90c7ba1&amp;dn=Sun+Tzu+-+The+Art+of+War&amp;tr=udp%3A%2F%2Ftracker.openbittorrent.com%3A80&amp;tr=udp%3A%2F%2Fopen.demonii.com%3A1337&amp;tr=udp%3A%2F%2Ftracker.coppersurfer.tk%3A6969&amp;tr=udp%3A%2F%2Fexodus.desync.com%3A6969","seeders":1,"leechers":0,"uploader":"]eep","files":2,"time":1274914937,"description":"Sun Tzu - The Art of War.","torrent":{"xt":"urn:btih:e8bd90f8227870d7a1644f4b4255ca54f90c7ba1","amp;dn":"Sun+Tzu+-+The+Art+of+War","amp;tr":["udp%3A%2F%2Ftracker.openbittorrent.com%3A80","udp%3A%2F%2Fopen.demonii.com%3A1337","udp%3A%2F%2Ftracker.coppersurfer.tk%3A6969","udp%3A%2F%2Fexodus.desync.com%3A6969"],"infoHash":"e8bd90f8227870d7a1644f4b4255ca54f90c7ba1","infoHashBuffer":{"type":"Buffer","data":[232,189,144,248,34,120,112,215,161,100,79,75,66,85,202,84,249,12,123,161]},"announce":[],"urlList":[]}}