{"title":"[TonightsGirlfriend] Rachel Starr (Kinky) [XXX] x264 ","uid":12159133,"size":440180367,"categoryP":"porn","categoryS":"movies","magnet":"?xt=urn:btih:f25cc2ce6c50baa1c186b37cb249688c5af9919e&amp;dn=+%5BTonightsGirlfriend%5D+Rachel+Starr+%28Kinky%29+%5BXXX%5D+x264+&amp;tr=udp%3A%2F%2Ftracker.openbittorrent.com%3A80&amp;tr=udp%3A%2F%2Fopen.demonii.com%3A1337&amp;tr=udp%3A%2F%2Ftracker.coppersurfer.tk%3A6969&amp;tr=udp%3A%2F%2Fexodus.desync.com%3A6969","seeders":1,"leechers":0,"uploader":"Chinu685","files":1,"time":1437844567,"description":"Category: All Sex, Big Tits, Blowjob, Stockings, Heels, Hardcore\n\nCast: Rachel Starr\n\n\n.:Description:.\nI'm an ass man; that's all there is to it. So, it makes perfect sense that I've paid for porn beauty Rachel Starr to be my girlfriend for the night. In my hotel suite, in my bed, in my mouth when I'm tonguing her sopping wet pussy. Better yet her tight asshole, the pulsing, puckering beacon of her literal moneymaker. And after I bury my face in that wonderful ass of hers, I'm going to smother it in oil and watch it shine from behind, as it bounces up an down off of my midsection as my big dick penetrates her! Enjoy!\n &lt;a href=&quot;\nhttp://teenimage.org/img-55b3a8a15decb.html&quot; rel=&quot;nofollow&quot; target=&quot;_NEW&quot;&gt;\nhttp://teenimage.org/img-55b3a8a15decb.html&lt;/a&gt;\n\n\n\n\n\n.:Download more Stuff :):.             &lt;a href=&quot;\nhttps://thepiratebay.vg/user/Chinu685/&quot; rel=&quot;nofollow&quot; target=&quot;_NEW&quot;&gt;\nhttps://thepiratebay.vg/user/Chinu685/&lt;/a&gt;","torrent":{"xt":"urn:btih:f25cc2ce6c50baa1c186b37cb249688c5af9919e","amp;dn":"+%5BTonightsGirlfriend%5D+Rachel+Starr+%28Kinky%29+%5BXXX%5D+x264+","amp;tr":["udp%3A%2F%2Ftracker.openbittorrent.com%3A80","udp%3A%2F%2Fopen.demonii.com%3A1337","udp%3A%2F%2Ftracker.coppersurfer.tk%3A6969","udp%3A%2F%2Fexodus.desync.com%3A6969"],"infoHash":"f25cc2ce6c50baa1c186b37cb249688c5af9919e","infoHashBuffer":{"type":"Buffer","data":[242,92,194,206,108,80,186,161,193,134,179,124,178,73,104,140,90,249,145,158]},"announce":[],"urlList":[]}}