{"title":"The.Super.Hero.Squad.Show.S01-S02.720p.WEB-DL.AAC.H264","uid":10722717,"size":11029032465,"categoryP":"video","categoryS":"hd___tv_shows","magnet":"?xt=urn:btih:f9c185799c0ab24ccc460018a1b7de9d3ad965b7&amp;dn=The.Super.Hero.Squad.Show.S01-S02.720p.WEB-DL.AAC.H264&amp;tr=udp%3A%2F%2Ftracker.openbittorrent.com%3A80&amp;tr=udp%3A%2F%2Fopen.demonii.com%3A1337&amp;tr=udp%3A%2F%2Ftracker.coppersurfer.tk%3A6969&amp;tr=udp%3A%2F%2Fexodus.desync.com%3A6969","seeders":1,"leechers":1,"uploader":"kronnnn","files":52,"time":1407508284,"description":"First off all credit goes to the original rip below. Re encoded to mp4 format for easy chrome casting and cut the size of the files by 2/3 (37gb to 10gb).\n &lt;a href=&quot;\nhttp://thepiratebay.se/torrent/7532565/The.Super.Hero.Squad.Show.S01.720p.WEB-DL.AAC2.0.DD5.1.H264-PYRO&quot; rel=&quot;nofollow&quot; target=&quot;_NEW&quot;&gt;\nhttp://thepiratebay.se/torrent/7532565/The.Super.Hero.Squad.Show.S01.720p.WEB-DL.AAC2.0.DD5.1.H264-PYRO&lt;/a&gt; &lt;a href=&quot;\nhttp://thepiratebay.se/torrent/7532569/The.Super.Hero.Squad.Show.S02.720p.WEB-DL.AAC2.0.DD5.1.H264-PYRO&quot; rel=&quot;nofollow&quot; target=&quot;_NEW&quot;&gt;\nhttp://thepiratebay.se/torrent/7532569/The.Super.Hero.Squad.Show.S02.720p.WEB-DL.AAC2.0.DD5.1.H264-PYRO&lt;/a&gt;\n\nFormat: MPEG4\nVideo: MPEG4 Video (H264) 1280x720 23.976fps\nAudio 1: AAC Flac 48000Hz stereo Bitrate 128\nConstant Quality: 25\n &lt;a href=&quot;\nhttp://bayimg.com/oapGhAafl&quot; rel=&quot;nofollow&quot; target=&quot;_NEW&quot;&gt;\nhttp://bayimg.com/oapGhAafl&lt;/a&gt; &lt;a href=&quot;\nhttp://bayimg.com/oApgJaAFl&quot; rel=&quot;nofollow&quot; target=&quot;_NEW&quot;&gt;\nhttp://bayimg.com/oApgJaAFl&lt;/a&gt; &lt;a href=&quot;\nhttp://bayimg.com/oaPgkAAfl&quot; rel=&quot;nofollow&quot; target=&quot;_NEW&quot;&gt;\nhttp://bayimg.com/oaPgkAAfl&lt;/a&gt;\n\nThe Super Hero Squad Show - Season 1 - Complete\n-----------------------------------------------\n\nWhen the greatest heroes on the planet unite to face the world's greatest villains,\nyou get the biggest, most family-friendly Super Hero team-up in TV history...\nSuper Hero Squad. It's no small job protecting Super Hero Cityfrom the wild,\nweird (and even wacky) villainy of VillainVille's infamous baddies... but\nIron Man, Wolverine, the Hulk, the Silver Surfer, Thor and the Falcon are\nalways up for the job. Shouting &quot;Hero Up!&quot; as they rush into battle,\nthe Squad must keep Dr.Doom's allies from gathering pieces of the Infinity Sword.\nOtherwise, Doom will use the Sword to rule the universe! Luckily, the City is\nfilled with Marvel super hero guest-stars to help out in a pinch. These brave\nheroes totally deliver the action - but with plenty of humor on the side.\n\nThe Super Hero Squad Show - Season 2 - Complete\n-----------------------------------------------\n\nJust when the Infinity Sword has been rebuilt, Doctor Doom is behind bars,\nand Villanville destroyed - a new evil threatens the universe...\nthe space-conqueror THANOS! Determined to prove his superiority over his sister,\nthe space-pirate NEBULA, Thanos sets out to collect the six INFINITY STONES.\nThe stones will give him absolute power over the universe, so the Squad must\nstop Thanos from collecting them in his INFINITY GAUNTLET before it's too late.\n\nProduced by Marvel Animation and Film Roman.\n\nS01E01 - And Lo... A Pilot Shall Come!\nS01E02 - To Err Is Superhuman!\nS01E03 - This Silver, This Surfer!\nS01E04 - Hulk Talk Smack!\nS01E05 - Enter: Dormammu!\nS01E06 - A Brat Walks Among Us!\nS01E07 - From the Atom... It Rises!\nS01E08 - Night In the Sanctorum!\nS01E09 - This Forest Green!\nS01E10 - O, Captain, My Captain!\nS01E11 - If This Be My Thanos!\nS01E12 - Deadly Is the Black Widow's Bite!\nS01E13 - Tremble At the Might of... M.O.D.O.K.!\nS01E14 - Mental Organism Designed Only For Kisses!\nS01E15 - Invader From The Dark Dimension!\nS01E16 - Tales Of Suspense!\nS01E17 - Stranger From A Savage Land!\nS01E18 - Mysterious Mayhem at Mutant High!\nS01E19 - Election of Evil!\nS01E20 - Oh, Brother!\nS01E21 - Hexed, Vexed and Perplexed!\nS01E22 - The Ice Melt Cometh!\nS01E23 - Wrath of the Red Skull!\nS01E24 - Mother of Doom!\nS01E25 - Last Exit Before Doomsday!\nS01E26 - This Al Dente Earth!\nS02E01 - Another Order of Evil!, Part 1\nS02E02 - Another Order of Evil!, Part 2\nS02E03 - Support Your Local Sky-Father!\nS02E04 - Villany Redux Syndrome!\nS02E05 - World War Witch!\nS02E06 - Whom Continuity Would Destroy!\nS02E07 - Double Negation at the World's End!\nS02E08 - Alienating With the Surfer!\nS02E09 - Blind Rage Knows No Color!\nS02E10 - Lo, How the Mighty Hath Abdicated!\nS02E11 - So Pretty When They Explode!\nS02E12 - Too Many Too Many Wolverines!\nS02E13 - Pedicure and Facial of Doom!\nS02E14 - Fate of Destiny!\nS02E15 - The Saga of Beta Ray Bill! (Six Against Infinity, Part 1)\nS02E16 - Days, Nights, and Weekends of Future Past! (Six Against Infinity, Part 2)\nS02E17 - This Man-Thing, This Monster! (Six Against Infinity, Part 3)\nS02E18 - The Devil Dinosaur You Say!\nS02E19 - Planet Hulk!\nS02E20 - 1602!\nS02E21 - Brouhaha At the World's Bottom!\nS02E22 - Missing: Impossible!\nS02E23 - Revenge of the Baby Sat!\nS02E24 - Soul Stone Picnic!\nS02E25 - When Strikes the Surfer!\nS02E26 - The Final Battle! ('Nuff Said!)","torrent":{"xt":"urn:btih:f9c185799c0ab24ccc460018a1b7de9d3ad965b7","amp;dn":"The.Super.Hero.Squad.Show.S01-S02.720p.WEB-DL.AAC.H264","amp;tr":["udp%3A%2F%2Ftracker.openbittorrent.com%3A80","udp%3A%2F%2Fopen.demonii.com%3A1337","udp%3A%2F%2Ftracker.coppersurfer.tk%3A6969","udp%3A%2F%2Fexodus.desync.com%3A6969"],"infoHash":"f9c185799c0ab24ccc460018a1b7de9d3ad965b7","infoHashBuffer":{"type":"Buffer","data":[249,193,133,121,156,10,178,76,204,70,0,24,161,183,222,157,58,217,101,183]},"announce":[],"urlList":[]}}