{"title":"ED SCHULTZ SHOW -- 11-20-2012","uid":7845272,"size":82112859,"categoryP":"audio","categoryS":"other","magnet":"?xt=urn:btih:fd0fd981e262d453c53646de803cb87262fd23de&amp;dn=ED+SCHULTZ+SHOW+--+11-20-2012&amp;tr=udp%3A%2F%2Ftracker.openbittorrent.com%3A80&amp;tr=udp%3A%2F%2Fopen.demonii.com%3A1337&amp;tr=udp%3A%2F%2Ftracker.coppersurfer.tk%3A6969&amp;tr=udp%3A%2F%2Fexodus.desync.com%3A6969","seeders":1,"leechers":0,"uploader":"TheExecutive","files":3,"time":1353455175,"description":".","torrent":{"xt":"urn:btih:fd0fd981e262d453c53646de803cb87262fd23de","amp;dn":"ED+SCHULTZ+SHOW+--+11-20-2012","amp;tr":["udp%3A%2F%2Ftracker.openbittorrent.com%3A80","udp%3A%2F%2Fopen.demonii.com%3A1337","udp%3A%2F%2Ftracker.coppersurfer.tk%3A6969","udp%3A%2F%2Fexodus.desync.com%3A6969"],"infoHash":"fd0fd981e262d453c53646de803cb87262fd23de","infoHashBuffer":{"type":"Buffer","data":[253,15,217,129,226,98,212,83,197,54,70,222,128,60,184,114,98,253,35,222]},"announce":[],"urlList":[]}}